{"0": [null, null, null, {"hotval": 5.84}, {"hotval": 8.9}, {"hotval": 0.96}, {"hotval": 3.39}, {"hotval": 19.3}, {"hotval": 1.95}, {"hotval": 1.86}, {"hotval": 6.93}, {"hotval": 6.84}], "1": [null, null, null, null, null, null, null, null, null, {"hotval": 0.87}, {"hotval": 4.89}, {"hotval": 7.31}, {"hotval": 1.69}, {"hotval": 2.99}, {"hotval": 0.93}, {"hotval": 0.06}, {"hotval": 0.0}, {"hotval": 0.86}, {"hotval": 0.58}, {"hotval": 18.4}, {"hotval": 1.93}, {"hotval": 0.95}, {"hotval": 2.78}, {"hotval": 3.32}, {"hotval": 10.95}], "2": [null, null, null, null, null, null, null, null, null, null, null, null, null, null, null, null, null, null, null, null, null, null, null, null, null, null, null, null, null, null, null, null, null, null, null, {"hotval": 9.84}, {"hotval": 2.41}, {"hotval": 7.32}, {"hotval": 7.44}, {"hotval": 2.71}, {"hotval": 6.0}, {"hotval": 4.22}, {"hotval": 0.53}, {"hotval": 0.35}, {"hotval": 9.08}, {"hotval": 5.5}, {"hotval": 1.6}, {"hotval": 2.42}, {"hotval": 0.19}, {"hotval": 5.18}, {"hotval": 1.39}, {"hotval": 0.43}, {"hotval": 0.85}, {"hotval": 0.19}, {"hotval": 6.2}, {"hotval": 0.78}, {"hotval": 0.06}, {"hotval": 0.33}, {"hotval": 1.5}, {"hotval": 0.34}, {"hotval": 0.0}, {"hotval": 0.06}, {"hotval": 1.48}, {"hotval": 3.58}, {"hotval": 1.35}, {"hotval": 4.89}, {"hotval": 0.87}, {"hotval": 1.5}, {"hotval": 0.29}, {"hotval": 7.57}, {"hotval": 0.61}, {"hotval": 3.16}, {"hotval": 0.21}, {"hotval": 1.71}, {"hotval": 0.88}, {"hotval": 0.17}, {"hotval": 6.58}, {"hotval": 6.89}, {"hotval": 2.12}, {"hotval": 3.85}], "3": [null, null, null, null, null, null, null, null, null, null, null, null, null, null, null, null, null, null, {"hotval": 0.27}, {"hotval": 3.64}, {"hotval": 4.27}, {"hotval": 0.06}, {"hotval": 0.36}, {"hotval": 2.4}, {"hotval": 29.35}, {"hotval": 11.0}, {"hotval": 61.42}, {"hotval": 14.14}, {"hotval": 10.62}], "4": [null, null, null, null, null, null, null, {"hotval": 12.05}, {"hotval": 11.53}, {"hotval": 2.38}], "5": [null, null, null, null, null, null, null, {"hotval": 5.94}, {"hotval": 8.31}, {"hotval": 0.42}], "6": [null, null, null, null, null, null, null, {"hotval": 12.62}, {"hotval": 14.67}, {"hotval": 0.09}, {"hotval": 3.47}, {"hotval": 1.62}, {"hotval": 1.65}, {"hotval": 0.65}, {"hotval": 0.17}, {"hotval": 0.03}, {"hotval": 0.43}], "7": [null, null, null, null, null, null, null, null, null, null, null, null, null, null, null, null, null, null, null, null, {"hotval": 3.83}, {"hotval": 28.86}, {"hotval": 4.52}, {"hotval": 0.18}, {"hotval": 9.47}, {"hotval": 1.4}, {"hotval": 0.09}, {"hotval": 1.27}, {"hotval": 0.03}, {"hotval": 3.4}, {"hotval": 0.6}, {"hotval": 0.03}, {"hotval": 0.0}, {"hotval": 3.9}, {"hotval": 21.34}, {"hotval": 1.74}, {"hotval": 10.4}, {"hotval": 4.01}, {"hotval": 56.53}, {"hotval": 4.36}], "8": [null], "9": [null, null, null, null, null, null, null, null, null, {"hotval": 3.3}, {"hotval": 4.37}, {"hotval": 2.54}, {"hotval": 2.01}, {"hotval": 1.93}, {"hotval": 1.76}, {"hotval": 12.09}, {"hotval": 0.96}, {"hotval": 1.05}, {"hotval": 4.04}, {"hotval": 0.89}, {"hotval": 6.64}], "10": [null, null, null, null, null, null, null, null, null, null, null, {"hotval": 6.15}, {"hotval": 14.02}, {"hotval": 8.86}, {"hotval": 6.96}, {"hotval": 5.54}, {"hotval": 1.43}], "11": [null], "12": [null, null, null, null, null, null, null, null, null, {"hotval": 4.58}, {"hotval": 18.2}, {"hotval": 0.24}], "13": [null], "14": [null, null, null, null, null, null, null, null, null, null, {"hotval": 156.42}, {"hotval": 3.38}, {"hotval": 3.07}, {"hotval": 7.91}, {"hotval": 1.89}, {"hotval": 0.32}, {"hotval": 0.03}, {"hotval": 0.48}, {"hotval": 3.1}, {"hotval": 6.75}, {"hotval": 10.69}, {"hotval": 1.46}, {"hotval": 6.57}, {"hotval": 4.3}], "15": [null], "16": [null, null, null, null, null, null, {"hotval": 0.82}, {"hotval": 1.15}, {"hotval": 2.23}, {"hotval": 6.35}, {"hotval": 0.03}, {"hotval": 0.22}, {"hotval": 2.28}, {"hotval": 1.44}], "17": [null], "18": [null, null, null, null, null, null, null, null, null, null, null, {"hotval": 2.8}, {"hotval": 1.97}, {"hotval": 1.54}, {"hotval": 5.6}, {"hotval": 0.09}, {"hotval": 6.97}, {"hotval": 1.1}, {"hotval": 3.06}, {"hotval": 7.06}, {"hotval": 155.84}, {"hotval": 4.74}, {"hotval": 16.4}, {"hotval": 14.65}, {"hotval": 3.63}, {"hotval": 2.27}], "19": [null, null, null, null, null, {"hotval": 280.79}, {"hotval": 527.42}, {"hotval": 178.77}, {"hotval": 30.4}, {"hotval": 87.9}, {"hotval": 0.0}, {"hotval": 1.15}, {"hotval": 2.49}, {"hotval": 49.19}, {"hotval": 1.88}, {"hotval": 8.85}, {"hotval": 3.49}, {"hotval": 113.68}], "20": [null], "21": [null, null, {"hotval": 146.45}, {"hotval": 8.17}, {"hotval": 5.33}, {"hotval": 8.75}, {"hotval": 5.71}, {"hotval": 14.21}, {"hotval": 3.48}, {"hotval": 2.82}], "22": [null, null, null, null, null, {"hotval": 20.34}, {"hotval": 21.54}, {"hotval": 11.59}, {"hotval": 12.36}], "23": [null, null, null, null, null, null, null, null, null, null, null, null, null, {"hotval": 213.6}], "24": [null, null, null, null, null, null, {"hotval": 3.2}, {"hotval": 8.07}, {"hotval": 6.39}, {"hotval": 5.22}, {"hotval": 1.28}, {"hotval": 1.09}, {"hotval": 8.33}, {"hotval": 0.0}, {"hotval": 1.25}, {"hotval": 31.59}, {"hotval": 13.76}], "25": [null, null, null, null, null, null, null, {"hotval": 5.81}, {"hotval": 7.35}, {"hotval": 6.5}, {"hotval": 35.82}, {"hotval": 14.43}, {"hotval": 8.69}], "26": [null], "27": [null], "28": [null, null, null, null, null, null, null, null, null, null, {"hotval": 65.7}, {"hotval": 1.54}, {"hotval": 8.94}, {"hotval": 2.91}, {"hotval": 6.63}, {"hotval": 6.87}, {"hotval": 7.21}, {"hotval": 3.99}, {"hotval": 17.72}, {"hotval": 6.46}, {"hotval": 5.33}, {"hotval": 1.14}, {"hotval": 0.06}, {"hotval": 9.49}, {"hotval": 8.99}], "29": [null, null, null, null, null, null, null, null, null, null, null, null, null, {"hotval": 2.56}, {"hotval": 7.07}, {"hotval": 2.12}, {"hotval": 1.4}, {"hotval": 1.06}, {"hotval": 0.51}, {"hotval": 0.16}, {"hotval": 5.85}, {"hotval": 9.03}, {"hotval": 0.25}, {"hotval": 2.67}], "30": [null, null, null, null, null, null, null, null, null, {"hotval": 2.07}, {"hotval": 0.22}, {"hotval": 12.89}, {"hotval": 2.76}, {"hotval": 0.0}, {"hotval": 0.44}, {"hotval": 162.8}, {"hotval": 226.58}, {"hotval": 21.85}], "31": [null], "32": [null], "33": [null, null, null, null, null, null, null, null], "34": [null], "35": [null], "36": [null], "37": [null], "38": [null], "39": [null], "40": [null, null, null, null, null, null, {"hotval": 19.64}, {"hotval": 15.19}, {"hotval": 2.85}, {"hotval": 0.06}, {"hotval": 1.53}, {"hotval": 23.68}, {"hotval": 12.25}, {"hotval": 2.21}, {"hotval": 27.56}], "41": [null], "42": [null], "43": [null], "44": [null, null, null, null, null, {"hotval": 1.08}, {"hotval": 1.81}, {"hotval": 6.65}, {"hotval": 4.56}], "45": [null], "46": [null], "47": [null], "48": [null], "49": [null], "50": [null, null, {"hotval": 3.98}, {"hotval": 13.8}, {"hotval": 6.79}, {"hotval": 8.29}, {"hotval": 10.25}, {"hotval": 11.77}, {"hotval": 37.16}, {"hotval": 0.77}, {"hotval": 1.69}, {"hotval": 0.06}], "51": [null], "52": [null, {"hotval": 8.85}, {"hotval": 4.11}, {"hotval": 13.83}, {"hotval": 10.12}, {"hotval": 5.07}, {"hotval": 4.67}, {"hotval": 1.12}, {"hotval": 26.38}, {"hotval": 34.86}], "53": [null, null, {"hotval": 3.37}, {"hotval": 21.75}, {"hotval": 1.06}, {"hotval": 11.72}, {"hotval": 0.0}, {"hotval": 5.26}], "54": [null], "55": [null, null, null, {"hotval": 13.4}, {"hotval": 29.14}, {"hotval": 0.0}, {"hotval": 53.0}, {"hotval": 15.23}], "56": [null], "57": [null], "58": [null], "59": [null, null, {"hotval": 35.1}, {"hotval": 18.44}, {"hotval": 1.61}, {"hotval": 17.05}, {"hotval": 6.96}, {"hotval": 11.05}, {"hotval": 9.8}, {"hotval": 15.54}, {"hotval": 43.23}, {"hotval": 63.32}, {"hotval": 37.72}], "60": [null, null, null, null, null, null, null, {"hotval": 156.3}, {"hotval": 0.96}, {"hotval": 14.34}, {"hotval": 6.92}, {"hotval": 2.65}, {"hotval": 14.74}, {"hotval": 0.25}, {"hotval": 14.49}, {"hotval": 2.02}, {"hotval": 3.96}, {"hotval": 3.73}, {"hotval": 1.47}, {"hotval": 2.76}, {"hotval": 18.75}, {"hotval": 0.57}, {"hotval": 26.87}, {"hotval": 17.05}], "61": [null], "62": [null], "63": [null], "64": [null], "65": [null, null, null, {"hotval": 107.39}, {"hotval": 15.56}, {"hotval": 143.47}, {"hotval": 6.44}, {"hotval": 16.28}, {"hotval": 3.23}, {"hotval": 43.13}, {"hotval": 8.94}, {"hotval": 6.65}], "66": [null], "67": [null], "68": [null, null, null, null, null, {"hotval": 0.3}, {"hotval": 0.0}], "69": [null], "70": [null, null, {"hotval": 17.2}, {"hotval": 1.7}, {"hotval": 0.06}, {"hotval": 4.21}, {"hotval": 0.03}, {"hotval": 2.26}], "71": [null], "72": [null], "73": [null], "74": [null, null, null, null, {"hotval": 2.9}, {"hotval": 4.66}, {"hotval": 12.78}, {"hotval": 8.73}, {"hotval": 12.09}, {"hotval": 7.82}], "75": [null], "76": [null], "77": [null], "78": [null, {"hotval": 3.95}, {"hotval": 0.29}, {"hotval": 0.09}], "79": [null, null, null, null, null, null, null, null, null, null, {"hotval": 6.78}, {"hotval": 0.38}, {"hotval": 14.0}, {"hotval": 5.48}, {"hotval": 2.35}, {"hotval": 0.57}], "80": [null, null, null, null, null, {"hotval": 5.83}, {"hotval": 14.45}, {"hotval": 1.65}, {"hotval": 1.86}], "81": [null], "82": [null], "83": [null], "84": [null], "85": [null], "86": [null], "87": [null, null, {"hotval": 3.8}, {"hotval": 2.13}, {"hotval": 7.33}, {"hotval": 6.19}, {"hotval": 0.22}, {"hotval": 2.8}], "88": [null, {"hotval": 15.79}, {"hotval": 2.57}, {"hotval": 1.38}, {"hotval": 26.87}, {"hotval": 1.11}, {"hotval": 13.72}], "89": [null], "90": [null, null, null, null, {"hotval": 5.44}, {"hotval": 0.69}, {"hotval": 3.54}, {"hotval": 0.0}, {"hotval": 4.23}], "91": [null], "92": [null], "93": [null, null, null, {"hotval": 14.77}, {"hotval": 3.04}, {"hotval": 0.63}, {"hotval": 17.77}, {"hotval": 20.42}], "94": [null], "95": [null, null, {"hotval": 0.0}, {"hotval": 4.06}, {"hotval": 1.56}, {"hotval": 1.66}, {"hotval": 3.65}], "96": [null], "97": [null, null, null, null, null, null, {"hotval": 10.57}, {"hotval": 2.99}, {"hotval": 12.47}, {"hotval": 7.57}, {"hotval": 5.46}], "98": [null, {"hotval": 13.81}, {"hotval": 7.38}, {"hotval": 0.12}, {"hotval": 2.39}, {"hotval": 7.08}, {"hotval": 719.29}, {"hotval": 7.96}], "99": [null], "100": [null], "101": [null], "102": [null], "103": [null], "104": [null], "105": [null], "106": [null], "107": [null], "108": [null], "109": [null], "110": [null], "111": [null], "112": [null], "113": [null], "114": [null], "115": [null], "116": [null], "117": [null], "118": [null], "119": [null], "120": [null], "121": [null], "122": [null, null, null, null, null, {"hotval": 22.21}, {"hotval": 2.09}], "123": [null], "124": [null], "125": [null, null, {"hotval": 8.98}, {"hotval": 4.3}, {"hotval": 5.25}, {"hotval": 0.68}, {"hotval": 10.53}, {"hotval": 0.09}, {"hotval": 2.5}, {"hotval": 1.19}, {"hotval": 9.16}, {"hotval": 12.13}, {"hotval": 7.55}, {"hotval": 5.07}, {"hotval": 30.86}], "126": [null], "127": [null], "128": [null, null, {"hotval": 6.39}, {"hotval": 6.65}, {"hotval": 8.95}, {"hotval": 28.56}], "129": [null], "130": [null], "131": [null], "132": [null], "133": [null], "134": [null], "135": [null], "136": [null, null, {"hotval": 5.5}, {"hotval": 5.76}, {"hotval": 0.45}, {"hotval": 1.72}, {"hotval": 2.76}, {"hotval": 2.76}], "137": [null], "138": [null], "139": [null], "140": [null], "141": [null], "142": [null], "143": [null], "144": [null], "145": [null, null, null, null, {"hotval": 2.04}], "146": [null], "147": [null], "148": [null, null, null, {"hotval": 15.64}, {"hotval": 8.04}, {"hotval": 17.34}, {"hotval": 4.27}, {"hotval": 5.44}, {"hotval": 4.71}], "149": [null], "150": [null], "151": [null, {"hotval": 6.7}, {"hotval": 7.43}, {"hotval": 7.06}], "152": [null, {"hotval": 0.63}, {"hotval": 2.48}, {"hotval": 9.82}, {"hotval": 21.99}, {"hotval": 4.35}, {"hotval": 3.57}, {"hotval": 33.67}, {"hotval": 2.58}, {"hotval": 20.04}, {"hotval": 20.6}], "153": [null], "154": [null, null, null, {"hotval": 11.34}, {"hotval": 11.76}, {"hotval": 0.29}, {"hotval": 4.25}, {"hotval": 1.17}, {"hotval": 7.37}, {"hotval": 17.18}], "155": [null, null, null, {"hotval": 13.08}, {"hotval": 3.9}, {"hotval": 0.0}, {"hotval": 7.64}], "156": [null], "157": [null], "158": [null, {"hotval": 28.38}, {"hotval": 11.6}, {"hotval": 26.63}, {"hotval": 47.12}, {"hotval": 76.4}, {"hotval": 19.76}, {"hotval": 8.16}, {"hotval": 0.54}, {"hotval": 19.36}, {"hotval": 2.54}, {"hotval": 0.09}, {"hotval": 5.86}, {"hotval": 5.32}, {"hotval": 12.98}, {"hotval": 41.82}, {"hotval": 6.61}, {"hotval": 14.96}, {"hotval": 1.25}, {"hotval": 8.51}, {"hotval": 2.64}], "159": [null], "160": [null, {"hotval": 0.42}, {"hotval": 2.06}, {"hotval": 1.65}, {"hotval": 0.45}, {"hotval": 0.93}, {"hotval": 0.0}, {"hotval": 1.58}, {"hotval": 3.95}, {"hotval": 1.19}, {"hotval": 3.24}, {"hotval": 0.09}], "161": [null], "162": [null], "163": [null], "164": [null], "165": [null], "166": [null], "167": [null], "168": [null], "169": [null], "170": [null], "171": [null], "172": [null], "173": [null], "174": [null], "175": [null], "176": [null], "177": [null], "178": [{"hotval": 142.32}], "179": [{"hotval": 172.78}, {"hotval": 25.4}, {"hotval": 23.85}, {"hotval": 31.62}, {"hotval": 39.43}, {"hotval": 18.91}, {"hotval": 12.86}, {"hotval": 0.89}, {"hotval": 5.56}, {"hotval": 8.92}, {"hotval": 0.06}, {"hotval": 3.65}, {"hotval": 4.98}, {"hotval": 4.5}, {"hotval": 21.09}, {"hotval": 3.72}, {"hotval": 4.56}], "180": [{"hotval": 240.02}], "181": [{"hotval": 127.78}], "182": [{"hotval": 99.82}], "183": [{"hotval": 639.05}, {"hotval": 31.04}, {"hotval": 6.31}, {"hotval": 2.26}, {"hotval": 1.77}, {"hotval": 55.89}, {"hotval": 50.46}, {"hotval": 30.19}, {"hotval": 106.75}, {"hotval": 26.45}, {"hotval": 17.76}], "184": [{"hotval": 95.68}, {"hotval": 3.38}, {"hotval": 5.78}, {"hotval": 0.23}, {"hotval": 175.96}], "185": [{"hotval": 17.87}], "186": [{"hotval": 2.92}], "187": [{"hotval": 15.24}], "188": [{"hotval": 34.59}], "189": [{"hotval": 2.83}], "190": [{"hotval": 2.76}], "191": [{"hotval": 8.39}], "192": [{"hotval": 8.39}], "193": [{"hotval": 9.89}], "194": [{"hotval": 4.55}], "195": [{"hotval": 29.52}], "196": [{"hotval": 4.49}], "197": [{"hotval": 4.46}, {"hotval": 0.03}, {"hotval": 0.03}, {"hotval": 0.9}, {"hotval": 4.16}, {"hotval": 1.36}, {"hotval": 1.09}, {"hotval": 2.49}], "198": [{"hotval": 2.08}], "199": [{"hotval": 5.78}], "200": [{"hotval": 85.64}], "201": [{"hotval": 14.21}], "202": [{"hotval": 25.19}], "203": [{"hotval": 17.5}], "204": [{"hotval": 24.7}], "205": [{"hotval": 1.39}, {"hotval": 1.96}, {"hotval": 0.34}, {"hotval": 3.01}, {"hotval": 1.17}, {"hotval": 1.06}, {"hotval": 0.06}, {"hotval": 8.76}, {"hotval": 2.68}, {"hotval": 2.01}, {"hotval": 3.9}, {"hotval": 3.12}, {"hotval": 0.06}], "206": [{"hotval": 17.1}], "207": [{"hotval": 12.8}], "208": [{"hotval": 11.44}], "209": [{"hotval": 0.52}], "210": [{"hotval": 0.25}], "211": [{"hotval": 0.06}], "212": [{"hotval": 2.43}], "213": [{"hotval": 0.0}, {"hotval": 2.23}, {"hotval": 31.81}, {"hotval": 1.53}, {"hotval": 1.66}, {"hotval": 1.25}, {"hotval": 7.17}, {"hotval": 2.39}, {"hotval": 2.1}, {"hotval": 18.24}, {"hotval": 10.24}], "214": [{"hotval": 2.31}], "215": [{"hotval": 1.87}], "216": [{"hotval": 9.15}, {"hotval": 0.78}, {"hotval": 0.97}, {"hotval": 1.29}, {"hotval": 0.03}, {"hotval": 0.28}, {"hotval": 5.47}, {"hotval": 0.09}, {"hotval": 1.98}, {"hotval": 4.13}, {"hotval": 0.36}], "217": [{"hotval": 18.31}], "218": [{"hotval": 15.8}], "219": [{"hotval": 9.46}], "220": [{"hotval": 3.8}], "221": [{"hotval": 2.05}], "222": [{"hotval": 11.0}], "223": [{"hotval": 1.65}], "224": [{"hotval": 1.52}, {"hotval": 0.3}, {"hotval": 0.89}], "225": [{"hotval": 10.81}], "226": [{"hotval": 2.74}], "227": [{"hotval": 23.02}], "228": [{"hotval": 16.31}], "229": [{"hotval": 5.34}, {"hotval": 0.57}, {"hotval": 0.62}, {"hotval": 0.09}, {"hotval": 26.63}, {"hotval": 12.36}, {"hotval": 28.35}, {"hotval": 36.92}, {"hotval": 58.37}, {"hotval": 28.83}], "230": [{"hotval": 3.87}], "231": [{"hotval": 15.02}], "232": [{"hotval": 25.66}], "233": [{"hotval": 13.65}], "234": [{"hotval": 20.47}], "235": [{"hotval": 4.5}], "236": [{"hotval": 14.91}], "237": [{"hotval": 3.82}], "238": [{"hotval": 7.69}], "239": [{"hotval": 12.8}], "240": [{"hotval": 5.56}], "241": [{"hotval": 8.46}], "242": [{"hotval": 7.12}], "243": [{"hotval": 2.16}], "244": [{"hotval": 0.03}], "245": [{"hotval": 6.26}], "246": [{"hotval": 2.51}, {"hotval": 0.35}, {"hotval": 0.27}, {"hotval": 1.0}, {"hotval": 4.49}, {"hotval": 0.36}, {"hotval": 1.32}, {"hotval": 1.44}], "247": [{"hotval": 2.72}], "248": [{"hotval": 5.74}], "249": [{"hotval": 0.97}], "250": [{"hotval": 0.06}], "251": [{"hotval": 4.92}], "252": [{"hotval": 2.35}], "253": [{"hotval": 7.17}], "254": [{"hotval": 1.15}], "255": [{"hotval": 3.19}], "256": [{"hotval": 0.25}], "257": [{"hotval": 4.48}], "258": [{"hotval": 0.64}], "259": [{"hotval": 0.0}], "260": [{"hotval": 0.47}], "261": [{"hotval": 1.76}], "262": [{"hotval": 8.97}, {"hotval": 6.73}, {"hotval": 7.06}, {"hotval": 3.65}, {"hotval": 163.42}, {"hotval": 2.87}, {"hotval": 34.87}, {"hotval": 86.97}, {"hotval": 83.12}], "263": [{"hotval": 16.75}], "264": [{"hotval": 2.41}], "265": [{"hotval": 1.86}], "266": [{"hotval": 0.36}], "267": [{"hotval": 15.41}], "268": [{"hotval": 0.98}], "269": [{"hotval": 4.3}], "270": [{"hotval": 3.17}], "271": [{"hotval": 0.2}], "272": [{"hotval": 0.0}, {"hotval": 14.04}, {"hotval": 8.92}], "273": [{"hotval": 3.63}, {"hotval": 13.15}, {"hotval": 10.65}, {"hotval": 27.33}], "274": [{"hotval": 2.03}], "275": [{"hotval": 10.5}], "276": [{"hotval": 0.38}], "277": [{"hotval": 5.53}], "278": [{"hotval": 1.13}, {"hotval": 24.97}, {"hotval": 6.71}, {"hotval": 17.5}], "279": [{"hotval": 14.03}], "280": [{"hotval": 23.79}], "281": [{"hotval": 1.03}], "282": [{"hotval": 0.06}], "283": [{"hotval": 0.09}], "284": [{"hotval": 0.27}], "285": [{"hotval": 2.76}], "286": [{"hotval": 8.54}], "287": [{"hotval": 0.86}], "288": [{"hotval": 0.15}], "289": [{"hotval": 7.5}], "290": [{"hotval": 1.72}], "291": [{"hotval": 8.11}], "292": [{"hotval": 11.76}], "293": [{"hotval": 8.17}], "294": [{"hotval": 1.23}], "295": [{"hotval": 23.75}], "296": [{"hotval": 1.18}], "297": [{"hotval": 0.55}], "298": [{"hotval": 4.8}], "299": [{"hotval": 0.06}], "300": [{"hotval": 0.06}], "301": [{"hotval": 5.3}], "302": [{"hotval": 1.5}], "303": [{"hotval": 5.21}], "304": [{"hotval": 2.76}], "305": [{"hotval": 3.32}], "306": [{"hotval": 20.59}], "307": [{"hotval": 1.89}], "308": [{"hotval": 0.09}], "309": [{"hotval": 0.18}], "310": [{"hotval": 0.29}], "311": [{"hotval": 2.52}], "312": [{"hotval": 0.0}], "313": [{"hotval": 11.77}], "314": [{"hotval": 1.62}], "315": [{"hotval": 1.92}], "316": [{"hotval": 0.19}], "317": [{"hotval": 0.03}], "318": [{"hotval": 11.92}], "319": [{"hotval": 0.19}], "320": [{"hotval": 6.28}], "321": [{"hotval": 11.5}], "322": [{"hotval": 2.67}], "323": [{"hotval": 6.69}], "324": [{"hotval": 8.32}], "325": [{"hotval": 0.0}], "326": [{"hotval": 1.92}], "327": [{"hotval": 46.56}], "328": [{"hotval": 1.14}], "329": [{"hotval": 2.85}], "330": [{"hotval": 4.96}], "331": [{"hotval": 0.03}], "332": [{"hotval": 424.84}], "333": [{"hotval": 2.07}], "334": [{"hotval": 1.99}], "335": [{"hotval": 7.92}, {"hotval": 3.01}, {"hotval": 0.8}], "336": [{"hotval": 2.04}], "337": [{"hotval": 21.9}], "338": [{"hotval": 5.06}], "339": [{"hotval": 7.39}], "340": [{"hotval": 9.31}], "341": [{"hotval": 23.75}], "342": [{"hotval": 2.96}], "343": [{"hotval": 0.48}], "344": [{"hotval": 15.2}], "345": [{"hotval": 13.93}], "346": [{"hotval": 4.84}], "347": [{"hotval": 8.55}], "348": [{"hotval": 4.96}], "349": [{"hotval": 17.03}], "350": [{"hotval": 1.12}], "351": [{"hotval": 14.2}], "352": [{"hotval": 26.94}], "353": [{"hotval": 24.31}], "354": [{"hotval": 34.7}], "355": [{"hotval": 29.32}], "356": [{"hotval": 30.28}], "357": [{"hotval": 31.93}], "358": [{"hotval": 0.57}], "359": [{"hotval": 1.47}], "360": [{"hotval": 30.72}], "361": [{"hotval": 12.65}], "362": [{"hotval": 2.44}, {"hotval": 2.47}, {"hotval": 1.3}], "363": [{"hotval": 9.46}], "364": [{"hotval": 13.24}], "365": [{"hotval": 10.91}], "366": [{"hotval": 15.31}], "367": [{"hotval": 12.64}], "368": [{"hotval": 15.8}], "369": [{"hotval": 12.31}], "370": [{"hotval": 23.18}], "371": [{"hotval": 20.19}], "372": [{"hotval": 6.42}], "373": [{"hotval": 7.67}, {"hotval": 7.21}, {"hotval": 9.4}, {"hotval": 9.47}, {"hotval": 1.94}, {"hotval": 25.27}, {"hotval": 8.12}, {"hotval": 109.48}, {"hotval": 261.68}, {"hotval": 30.95}, {"hotval": 65.86}, {"hotval": 21.62}], "374": [{"hotval": 33.79}], "375": [{"hotval": 36.17}], "376": [{"hotval": 5.04}], "377": [{"hotval": 7.02}], "378": [{"hotval": 9.09}], "379": [{"hotval": 2.96}], "380": [{"hotval": 10.77}], "381": [{"hotval": 1.57}], "382": [{"hotval": 20.91}], "383": [{"hotval": 3.06}], "384": [{"hotval": 1.16}], "385": [{"hotval": 2.95}], "386": [{"hotval": 0.73}], "387": [{"hotval": 3.11}], "388": [{"hotval": 6.84}], "389": [{"hotval": 5.0}], "390": [{"hotval": 26.05}], "391": [{"hotval": 20.62}], "392": [{"hotval": 6.65}], "393": [{"hotval": 7.07}], "394": [{"hotval": 3.2}], "395": [{"hotval": 14.76}], "396": [{"hotval": 7.14}], "397": [{"hotval": 12.75}], "398": [{"hotval": 0.74}], "399": [{"hotval": 2.7}], "400": [{"hotval": 6.03}], "401": [{"hotval": 0.0}], "402": [{"hotval": 1.3}], "403": [{"hotval": 91.99}], "404": [{"hotval": 39.13}], "405": [{"hotval": 43.74}], "406": [{"hotval": 28.25}], "407": [{"hotval": 4.2}], "408": [{"hotval": 14.86}], "409": [{"hotval": 21.71}], "410": [{"hotval": 194.39}], "411": [{"hotval": 8.09}], "412": [{"hotval": 10.8}], "413": [{"hotval": 0.24}], "414": [{"hotval": 0.0}]}